setup.py
mess_server_january.egg-info/PKG-INFO
mess_server_january.egg-info/SOURCES.txt
mess_server_january.egg-info/dependency_links.txt
mess_server_january.egg-info/requires.txt
mess_server_january.egg-info/top_level.txt
server/__init__.py
server/server.py
server/common/__init__.py
server/common/decos.py
server/common/descrptrs.py
server/common/errors.py
server/common/metaclasses.py
server/common/utils.py
server/common/variables.py
server/server/__init__.py
server/server/add_user.py
server/server/config_window.py
server/server/core.py
server/server/main_window.py
server/server/remove_user.py
server/server/server_db.py
server/server/stat_window.py
server/unit_tests/__init__.py
server/unit_tests/test_client.py
server/unit_tests/test_server.py
server/unit_tests/test_utils.py