Metadata-Version: 1.0
Name: mess-server-january
Version: 0.0.1
Summary: mess_server_january
Home-page: UNKNOWN
Author: Oleg Dementev
Author-email: demeoleg@yandex.ru
License: UNKNOWN
Platform: UNKNOWN
